political_ml/__init__.py
political_ml/__meta__.py
political_ml/client.py
political_ml/utils.py
political_ml-0.4.0.dist-info/METADATA
political_ml-0.4.0.dist-info/WHEEL
political_ml-0.4.0.dist-info/top_level.txt
political_ml-0.4.0.dist-info/RECORD
