Metadata-Version: 2.1
Name: political-ml
Version: 0.4.0
Summary: An API wrapper for a set of API's related to NLP.
Home-page: https://github.com/wepublic-nl
Author: Wepublic
License: Other/Proprietary License
Project-URL: Source, https://github.com/wepublic-nl/political_ml
Platform: UNKNOWN
Classifier: Development Status :: 5 - Production/Stable
Classifier: Intended Audience :: Developers
Classifier: Natural Language :: English
Classifier: Programming Language :: Python
Classifier: Programming Language :: Python :: 3
Classifier: Programming Language :: Python :: 3.8
Classifier: Programming Language :: Python :: 3.9
Classifier: Programming Language :: Python :: 3.10
Classifier: Programming Language :: Python :: Implementation :: CPython
Classifier: Programming Language :: Python :: Implementation :: PyPy
Requires-Python: >= 3.8
Requires-Dist: requests (>=2.25.1)
Provides-Extra: dev
Requires-Dist: pytest (>=6.2.5) ; extra == 'dev'
Requires-Dist: coverage (==5.5) ; extra == 'dev'
Requires-Dist: pre-commit (==2.12.0) ; extra == 'dev'
Requires-Dist: twine (~=3.4) ; extra == 'dev'
Requires-Dist: build (~=0.7) ; extra == 'dev'
Provides-Extra: test
Requires-Dist: pytest (>=6.2.5) ; extra == 'test'
Requires-Dist: coverage (==5.5) ; extra == 'test'
